gitcrumbs/__init__.py
gitcrumbs/cli.py
gitcrumbs/utils.py
gitcrumbs-0.1.8.dist-info/licenses/LICENSE
gitcrumbs-0.1.8.dist-info/METADATA
gitcrumbs-0.1.8.dist-info/WHEEL
gitcrumbs-0.1.8.dist-info/entry_points.txt
gitcrumbs-0.1.8.dist-info/top_level.txt
gitcrumbs-0.1.8.dist-info/RECORD
