Metadata-Version: 2.4
Name: gitcrumbs
Version: 0.1.8
Summary: A CLI tool that captures intermediate working states of your Git repo in-between commits.
Author-email: Ertelek <contact.ertelek@yahoo.com>
License: MIT
Project-URL: Homepage, https://github.com/ertelek/gitcrumbs
Project-URL: Repository, https://github.com/ertelek/gitcrumbs
Project-URL: Issues, https://github.com/ertelek/gitcrumbs/issues
Keywords: git,cli,developer-tools,productivity,snapshots,version-control
Classifier: Development Status :: 4 - Beta
Classifier: Intended Audience :: Developers
Classifier: License :: OSI Approved :: MIT License
Classifier: Programming Language :: Python :: 3
Classifier: Programming Language :: Python :: 3 :: Only
Classifier: Programming Language :: Python :: 3.9
Classifier: Programming Language :: Python :: 3.10
Classifier: Programming Language :: Python :: 3.11
Classifier: Programming Language :: Python :: 3.12
Classifier: Environment :: Console
Classifier: Operating System :: OS Independent
Classifier: Topic :: Software Development :: Version Control :: Git
Classifier: Topic :: Utilities
Requires-Python: >=3.9
License-File: LICENSE
Requires-Dist: typer<1.0,>=0.12
Requires-Dist: rich<14,>=13
Requires-Dist: watchdog>=6.0.0
Dynamic: license-file
